plone.keyring-4.0.3-py3.13-nspkg.pth
plone/keyring/__init__.py
plone/keyring/configure.zcml
plone/keyring/django_random.py
plone/keyring/interfaces.py
plone/keyring/keymanager.py
plone/keyring/keyring.py
plone/keyring/meta.zcml
plone/keyring/profiles/default/componentregistry.xml
plone/keyring/profiles/default/metadata.xml
plone/keyring/tests/__init__.py
plone/keyring/tests/testKeymanager.py
plone/keyring/tests/testKeyring.py
plone_keyring-4.0.3.dist-info/METADATA
plone_keyring-4.0.3.dist-info/WHEEL
plone_keyring-4.0.3.dist-info/namespace_packages.txt
plone_keyring-4.0.3.dist-info/top_level.txt
plone_keyring-4.0.3.dist-info/RECORD
